asvcore-0.0.1.dist-info/METADATA
asvcore-0.0.1.dist-info/WHEEL
asvcore/__init__.py
asvcore/aux.py
asvcore/benchmarks/__init__.py
asvcore/benchmarks/_base.py
asvcore/benchmarks/_exceptions.py
asvcore/benchmarks/_maxrss.py
asvcore/benchmarks/mem.py
asvcore/benchmarks/peakmem.py
asvcore/benchmarks/time.py
asvcore/benchmarks/timeraw.py
asvcore/benchmarks/track.py
asvcore/check.py
asvcore/discovery.py
asvcore/run.py
asvcore/server.py
asvcore/setup_cache.py
asvcore/timing.py
asvcore-0.0.1.dist-info/RECORD
