Metadata-Version: 2.1
Name: asvcore
Version: 0.0.1
Summary: Core Python benchmark code for ASV
Author-Email: Rohit Goswami <rog32@hi.is>
Maintainer-Email: Rohit Goswami <rog32@hi.is>
License: MIT
Requires-Python: >=3.7
Provides-Extra: lint
Requires-Dist: ruff>=0.0.265; extra == "lint"
Requires-Dist: black>=23.3.0; extra == "lint"
